secretpy/__init__.py
secretpy/abstractmachine.py
secretpy/alphabets.py
secretpy/compositemachine.py
secretpy/cryptmachine.py
secretpy/ciphers/__init__.py
secretpy/ciphers/adfgvx.py
secretpy/ciphers/adfgx.py
secretpy/ciphers/affine.py
secretpy/ciphers/atbash.py
secretpy/ciphers/autokey.py
secretpy/ciphers/bazeries.py
secretpy/ciphers/beaufort.py
secretpy/ciphers/bifid.py
secretpy/ciphers/caesar.py
secretpy/ciphers/caesar_progressive.py
secretpy/ciphers/chao.py
secretpy/ciphers/columnar_transposition.py
secretpy/ciphers/four_square.py
secretpy/ciphers/gronsfeld.py
secretpy/ciphers/keyword.py
secretpy/ciphers/myszkowski_transposition.py
secretpy/ciphers/nihilist.py
secretpy/ciphers/playfair.py
secretpy/ciphers/polybius.py
secretpy/ciphers/polybius_square.py
secretpy/ciphers/porta.py
secretpy/ciphers/rot13.py
secretpy/ciphers/rot18.py
secretpy/ciphers/rot47.py
secretpy/ciphers/rot5.py
secretpy/ciphers/scytale.py
secretpy/ciphers/simplesubstitution.py
secretpy/ciphers/spiral.py
secretpy/ciphers/three_square.py
secretpy/ciphers/trifid.py
secretpy/ciphers/two_square.py
secretpy/ciphers/vic.py
secretpy/ciphers/vigenere.py
secretpy/ciphers/zigzag.py
secretpy/cmdecorators/__init__.py
secretpy/cmdecorators/block.py
secretpy/cmdecorators/decorator.py
secretpy/cmdecorators/save_all.py
secretpy/cmdecorators/savecase.py
secretpy/cmdecorators/uppercase.py
secretpy-0.12.0.dist-info/DESCRIPTION.rst
secretpy-0.12.0.dist-info/METADATA
secretpy-0.12.0.dist-info/RECORD
secretpy-0.12.0.dist-info/WHEEL
secretpy-0.12.0.dist-info/metadata.json
secretpy-0.12.0.dist-info/top_level.txt
