Metadata-Version: 2.0
Name: secretpy
Version: 0.12.0
Summary: Classical ciphers
Home-page: https://github.com/tigertv/secretpy
Author: Max Vetrov
Author-email: maxvetrov555@yandex.ru
License: UNKNOWN
Project-URL: Source code, https://github.com/tigertv/secretpy
Project-URL: Documentation, https://secretpy.readthedocs.io
Project-URL: Bug tracker, https://github.com/tigertv/secretpy/issues
Keywords: classic ciphers cipher secret
Platform: UNKNOWN
Classifier: Development Status :: 3 - Alpha
Classifier: License :: OSI Approved :: MIT License
Classifier: Intended Audience :: Developers
Classifier: Intended Audience :: Education
Classifier: Intended Audience :: Science/Research
Classifier: Intended Audience :: End Users/Desktop
Classifier: Intended Audience :: Other Audience
Classifier: Topic :: Security :: Cryptography
Classifier: Topic :: Software Development :: Libraries :: Python Modules
Classifier: Topic :: Education
Classifier: Operating System :: OS Independent
Classifier: Programming Language :: Python :: 2.7
Classifier: Programming Language :: Python :: 3.4
Classifier: Programming Language :: Python :: 3.5
Classifier: Programming Language :: Python :: 3.6
Classifier: Programming Language :: Python :: 3.7
Classifier: Programming Language :: Python :: 3.8
Classifier: Programming Language :: Python :: 3.9
Classifier: Programming Language :: Python :: Implementation :: CPython
Classifier: Programming Language :: Python :: Implementation :: PyPy
